autopredictor/__init__.py
autopredictor/bestscore.py
autopredictor/fit.py
autopredictor/select_model.py
autopredictor/show_all.py
autopredictor-0.2.3.dist-info/LICENSE
autopredictor-0.2.3.dist-info/METADATA
autopredictor-0.2.3.dist-info/WHEEL
autopredictor-0.2.3.dist-info/RECORD
