Metadata-Version: 2.1
Name: autopredictor
Version: 0.2.3
Summary: A package that streamline the repetitive task of regression models selection and comparison in the machine learning workflow.
License: GNU GPL 3
Author: Anu Banga, Arturo Rey, Sharon Voon, Zeily Garcia
Requires-Python: >=3.9,<4.0
Classifier: License :: Other/Proprietary License
Classifier: Programming Language :: Python :: 3
Classifier: Programming Language :: Python :: 3.9
Classifier: Programming Language :: Python :: 3.10
Classifier: Programming Language :: Python :: 3.11
Classifier: Programming Language :: Python :: 3.12
Requires-Dist: pandas (>=2.1.4,<3.0.0)
Requires-Dist: scikit-learn (>=1.3.2,<2.0.0)
Requires-Dist: tabulate (>=0.9.0,<0.10.0)
